aplus
switchboard
