Metadata-Version: 1.1
Name: switchboard-python
Version: 0.1.1
Summary: Python switchboard utilites
Home-page: https://github.com/jtmoulia/switchboard-python
Author: jtmoulia
Author-email: jtmoulia@pocketknife.io
License: Copyright (c) 2014, Spatch
